helloworld.py
helloworld_examplePackage-0.0.1.dist-info/LICENSE.txt
helloworld_examplePackage-0.0.1.dist-info/METADATA
helloworld_examplePackage-0.0.1.dist-info/WHEEL
helloworld_examplePackage-0.0.1.dist-info/top_level.txt
helloworld_examplePackage-0.0.1.dist-info/RECORD
