Metadata-Version: 2.1
Name: helloworld-examplePackage
Version: 0.0.1
Summary: Say hello!
Home-page: https://github.com/drewamorbordelon/helloworld-PyPI
Author: Drew Bordelon
Author-email: bordelon.drew@gmail.com
License: UNKNOWN
Platform: UNKNOWN
Classifier: Programming Language :: Python :: 3
Classifier: Programming Language :: Python :: 3.6
Classifier: Programming Language :: Python :: 3.7
Classifier: Programming Language :: Python :: 3.8
Classifier: License :: OSI Approved :: MIT License
Classifier: Operating System :: OS Independent
Provides-Extra: dev
Requires-Dist: pytest (>=3.8) ; extra == 'dev'
Requires-Dist: twine ; extra == 'dev'
